{"kind":"ROperator","id":"0d165c3cc1b423d5e64802f8560127c0","isDeleted":false,"rev":"1-2f4a65dd37d552daa2321be2d4409c9e","description":"Hierarchical Cluster","name":"hclust","createdBy":"ger.inberg","acl":{"kind":"Acl","owner":"ger.inberg","aces":[]},"createdDate":{"kind":"Date","value":"2021-11-23T13:15:14.885351Z"},"lastModifiedDate":{"kind":"Date","value":"2021-11-23T13:15:14.885351Z"},"urls":[{"kind":"Url","uri":"https://github.com/tercen/hclust_operator"}],"tags":["multivariate statistics"],"meta":[{"kind":"Pair","key":"runtime","value":"R-3.5"}],"url":{"kind":"Url","uri":"https://github.com/tercen/hclust_operator"},"version":"0.10.0","authors":["tercen"],"isPublic":true,"properties":[{"kind":"BooleanProperty","name":"scale","description":"A logical value indicating whether the variables should be scaled to have unit variance before the analysis takes place.","defaultValue":false},{"kind":"BooleanProperty","name":"center","description":"A logical value indicating whether the variables should be shifted to be zero centered.","defaultValue":false},{"kind":"DoubleProperty","name":"fill","description":"Value with which to fill in structural missings.","defaultValue":0.0}],"longDescription":"","path":"/var/lib/tercen/data/operator/ac/dd/2c/2cddacc5-7155-4eec-982a-117cbc34fd5e/tercen-hclust_operator-cbae843"}